sstable_tools/__init__.py
sstable_tools/sstablelib.py
sstable_tools/statistics.py
sstable_tools-0.0.2.data/scripts/sstable-compressioninfo.py
sstable_tools-0.0.2.data/scripts/sstable-index.py
sstable_tools-0.0.2.data/scripts/sstable-statistics.py
sstable_tools-0.0.2.data/scripts/sstable-summary.py
sstable_tools-0.0.2.dist-info/LICENSE
sstable_tools-0.0.2.dist-info/METADATA
sstable_tools-0.0.2.dist-info/WHEEL
sstable_tools-0.0.2.dist-info/top_level.txt
sstable_tools-0.0.2.dist-info/RECORD
